odoo8_addon_hr_payroll_email_slip-8.0.1.0.0.99.dev8-py3.8-nspkg.pth
odoo_addons/hr_payroll_email_slip/README.rst
odoo_addons/hr_payroll_email_slip/__init__.py
odoo_addons/hr_payroll_email_slip/__openerp__.py
odoo_addons/hr_payroll_email_slip/data/payslip_emailtemplate.xml
odoo_addons/hr_payroll_email_slip/i18n/ar.po
odoo_addons/hr_payroll_email_slip/i18n/bg.po
odoo_addons/hr_payroll_email_slip/i18n/bs.po
odoo_addons/hr_payroll_email_slip/i18n/ca.po
odoo_addons/hr_payroll_email_slip/i18n/cs.po
odoo_addons/hr_payroll_email_slip/i18n/da.po
odoo_addons/hr_payroll_email_slip/i18n/da_DK.po
odoo_addons/hr_payroll_email_slip/i18n/de.po
odoo_addons/hr_payroll_email_slip/i18n/el_GR.po
odoo_addons/hr_payroll_email_slip/i18n/en_GB.po
odoo_addons/hr_payroll_email_slip/i18n/es.po
odoo_addons/hr_payroll_email_slip/i18n/es_AR.po
odoo_addons/hr_payroll_email_slip/i18n/es_CL.po
odoo_addons/hr_payroll_email_slip/i18n/es_CO.po
odoo_addons/hr_payroll_email_slip/i18n/es_CR.po
odoo_addons/hr_payroll_email_slip/i18n/es_DO.po
odoo_addons/hr_payroll_email_slip/i18n/es_EC.po
odoo_addons/hr_payroll_email_slip/i18n/es_MX.po
odoo_addons/hr_payroll_email_slip/i18n/es_PE.po
odoo_addons/hr_payroll_email_slip/i18n/es_PY.po
odoo_addons/hr_payroll_email_slip/i18n/es_VE.po
odoo_addons/hr_payroll_email_slip/i18n/et.po
odoo_addons/hr_payroll_email_slip/i18n/fa.po
odoo_addons/hr_payroll_email_slip/i18n/fi.po
odoo_addons/hr_payroll_email_slip/i18n/fr.po
odoo_addons/hr_payroll_email_slip/i18n/gl.po
odoo_addons/hr_payroll_email_slip/i18n/he.po
odoo_addons/hr_payroll_email_slip/i18n/hr.po
odoo_addons/hr_payroll_email_slip/i18n/hr_HR.po
odoo_addons/hr_payroll_email_slip/i18n/hr_payroll_email_slip.pot
odoo_addons/hr_payroll_email_slip/i18n/hu.po
odoo_addons/hr_payroll_email_slip/i18n/id.po
odoo_addons/hr_payroll_email_slip/i18n/it.po
odoo_addons/hr_payroll_email_slip/i18n/ja.po
odoo_addons/hr_payroll_email_slip/i18n/ko.po
odoo_addons/hr_payroll_email_slip/i18n/lt.po
odoo_addons/hr_payroll_email_slip/i18n/lv.po
odoo8_addon_hr_payroll_email_slip-8.0.1.0.0.99.dev8.dist-info/METADATA
odoo8_addon_hr_payroll_email_slip-8.0.1.0.0.99.dev8.dist-info/WHEEL
odoo8_addon_hr_payroll_email_slip-8.0.1.0.0.99.dev8.dist-info/namespace_packages.txt
odoo8_addon_hr_payroll_email_slip-8.0.1.0.0.99.dev8.dist-info/top_level.txt
odoo8_addon_hr_payroll_email_slip-8.0.1.0.0.99.dev8.dist-info/RECORD
